devtools_keyboard_shortcuts/__init__.py
devtools_keyboard_shortcuts-1.0.1.dist-info/METADATA
devtools_keyboard_shortcuts-1.0.1.dist-info/WHEEL
devtools_keyboard_shortcuts-1.0.1.dist-info/top_level.txt
devtools_keyboard_shortcuts-1.0.1.dist-info/RECORD
