Metadata-Version: 2.1
Name: devtools-keyboard-shortcuts
Version: 1.0.1
Summary: Keyboard shortcuts reference
Home-page: https://devtools.at/tools/keyboard-shortcuts
Author: DevTools.at
Author-email: hello@devtools.at
Project-URL: Homepage, https://devtools.at/tools/keyboard-shortcuts
Project-URL: Repository, https://github.com/devtools-at/keyboard-shortcuts
Classifier: Development Status :: 4 - Beta
Classifier: Intended Audience :: Developers
Classifier: License :: OSI Approved :: MIT License
Classifier: Programming Language :: Python :: 3
Requires-Python: >=3.8
